pyparts_utility/__init__.py
pyparts_utility/formating.py
pyparts_utility/main.py
pyparts_utility-0.1.0.dist-info/entry_points.txt
pyparts_utility-0.1.0.dist-info/WHEEL
pyparts_utility-0.1.0.dist-info/METADATA
pyparts_utility-0.1.0.dist-info/RECORD
